homage/__init__.py
homage/main.py
homage_to_the_square-1.1.0.dist-info/METADATA
homage_to_the_square-1.1.0.dist-info/WHEEL
homage_to_the_square-1.1.0.dist-info/entry_points.txt
homage_to_the_square-1.1.0.dist-info/top_level.txt
homage_to_the_square-1.1.0.dist-info/RECORD
