Metadata-Version: 2.1
Name: homage-to-the-square
Version: 1.1.0
Summary: runs an homage to the square a la josef albers
Home-page: https://github.com/talnoznisky/homage-to-the-square
Author: Tal Noznisky
License: MIT
Platform: UNKNOWN
Requires-Python: >=3.0
